wanstatus/__init__.py
wanstatus/wanstatus.py
wanstatus/deployment_files/creds_SMTP
wanstatus/deployment_files/creds_wanstatus
wanstatus/deployment_files/wanstatus.cfg
wanstatus/deployment_files/wanstatus.service
wanstatus-3.1.2.dist-info/licenses/LICENSE.txt
wanstatus-3.1.2.dist-info/METADATA
wanstatus-3.1.2.dist-info/WHEEL
wanstatus-3.1.2.dist-info/entry_points.txt
wanstatus-3.1.2.dist-info/top_level.txt
wanstatus-3.1.2.dist-info/RECORD
