Metadata-Version: 2.4
Name: wanstatus
Version: 3.1.2
Summary: Monitor WAN-side internet access and WAN IP address changes on a home network
Author-email: Chris Nelson <github@cjnaz.com>
License-Expression: MIT
Project-URL: repository, https://github.com/cjnaz/wanstatus
Keywords: cjnaz,lan,wan,router,pfsense,dd-wrt,monitor
Classifier: Topic :: System :: Networking :: Monitoring
Requires-Python: >=3.9
License-File: LICENSE.txt
Requires-Dist: requests
Requires-Dist: cjnfuncs>=3.1rc4
Dynamic: license-file
